ibis_bench/__init__.py
ibis_bench/cli.py
ibis_bench/cli2.py
ibis_bench/tpcds/queries/ibis.py
ibis_bench/tpcds/queries/polars.py
ibis_bench/tpcds/queries/sql.py
ibis_bench/tpcds/utils/gen_data.py
ibis_bench/tpcds/utils/logging.py
ibis_bench/tpcds/utils/monitor.py
ibis_bench/tpcds/utils/read_data.py
ibis_bench/tpcds/utils/write_data.py
ibis_bench/tpch/queries/ibis.py
ibis_bench/tpch/queries/polars.py
ibis_bench/tpch/queries/sql.py
ibis_bench/tpch/utils/gen_data.py
ibis_bench/tpch/utils/logging.py
ibis_bench/tpch/utils/monitor.py
ibis_bench/tpch/utils/read_data.py
ibis_bench/tpch/utils/write_data.py
ibis_bench/utils/gen_data.py
ibis_bench/utils/logging.py
ibis_bench/utils/monitor.py
ibis_bench/utils/read_data.py
ibis_bench/utils/write_data.py
ibis_bench-0.2.0.dist-info/METADATA
ibis_bench-0.2.0.dist-info/WHEEL
ibis_bench-0.2.0.dist-info/entry_points.txt
ibis_bench-0.2.0.dist-info/RECORD
